wideboost/__init__.py
wideboost/helpers.py
wideboost/evals/__init__.py
wideboost/evals/classification.py
wideboost/evals/regression.py
wideboost/explainers/__init__.py
wideboost/explainers/shap.py
wideboost/objectives/__init__.py
wideboost/objectives/binarylogloss.py
wideboost/objectives/categoricallogloss.py
wideboost/objectives/general_gh.py
wideboost/objectives/manybinarylogloss.py
wideboost/objectives/squareloss.py
wideboost/objectives/tests/__init__.py
wideboost/objectives/tests/test_binarylogloss.py
wideboost/objectives/tests/test_categoricallogloss.py
wideboost/objectives/tests/test_squareloss.py
wideboost/parameters/B.py
wideboost/parameters/__init__.py
wideboost/tests/__init__.py
wideboost/tests/test_dummy.py
wideboost/wrappers/__init__.py
wideboost/wrappers/wlgb.py
wideboost/wrappers/wxgb.py
wideboost/wrappers/wxgb_sklearn.py
wideboost-0.4.2.dist-info/LICENSE
wideboost-0.4.2.dist-info/METADATA
wideboost-0.4.2.dist-info/WHEEL
wideboost-0.4.2.dist-info/top_level.txt
wideboost-0.4.2.dist-info/RECORD
