Metadata-Version: 2.1
Name: wideboost
Version: 0.4.2
Summary: Implements Wide Boosting functions for popular boosting packages
Home-page: https://github.com/mthorrell/wideboost
Author: Michael Horrell
Author-email: mthorrell@github.com
Classifier: Programming Language :: Python :: 3
Classifier: License :: OSI Approved :: MIT License
Classifier: Operating System :: OS Independent
Requires-Python: >=3.6
License-File: LICENSE
Requires-Dist: numpy
Requires-Dist: xgboost
Requires-Dist: scikit-learn
Provides-Extra: lightgbm
Requires-Dist: lightgbm ; extra == 'lightgbm'
Provides-Extra: shap
Requires-Dist: shap ; extra == 'shap'
